ruamel/yaml/string/__init__.py
ruamel/yaml/string/__plug_in__.py
ruamel.yaml.string-0.1.0.dist-info/LICENSE
ruamel.yaml.string-0.1.0.dist-info/METADATA
ruamel.yaml.string-0.1.0.dist-info/WHEEL
ruamel.yaml.string-0.1.0.dist-info/namespace_packages.txt
ruamel.yaml.string-0.1.0.dist-info/top_level.txt
ruamel.yaml.string-0.1.0.dist-info/RECORD
