Metadata-Version: 2.1
Name: ruamel.yaml.string
Version: 0.1.0
Summary: add dump_to_string/dumps method that returns YAML document as string
Home-page: https://sourceforge.net/p/ruamel-yaml-string/code/ci/default/tree
Author: Anthon van der Neut
Author-email: a.van.der.neut@ruamel.eu
License: MIT
Keywords: yaml 1.2 dump python string
Platform: UNKNOWN
Classifier: Development Status :: 4 - Beta
Classifier: Intended Audience :: Developers
Classifier: License :: OSI Approved :: MIT License
Classifier: Operating System :: OS Independent
Classifier: Programming Language :: Python
Requires-Python: >=3
License-File: LICENSE
Requires-Dist: ruamel.yaml (>=0.17.17)
